toolkitify/__init__.py
toolkitify-0.0.2.dist-info/METADATA
toolkitify-0.0.2.dist-info/WHEEL
toolkitify-0.0.2.dist-info/top_level.txt
toolkitify-0.0.2.dist-info/RECORD
