Metadata-Version: 2.4
Name: toolkitify
Version: 0.0.2
Summary: Everything you need for your project.
Home-page: https://github.com/TPEOficial/dymo-api-python
Author: TPEOficial LLC
Author-email: support@tpeoficial.com
License: Apache-2.0
Classifier: Programming Language :: Python :: 3
Classifier: License :: OSI Approved :: Apache Software License
Classifier: Operating System :: OS Independent
Requires-Python: >=3.6
Dynamic: author
Dynamic: author-email
Dynamic: classifier
Dynamic: description
Dynamic: description-content-type
Dynamic: home-page
Dynamic: license
Dynamic: requires-python
Dynamic: summary
